adbpy/__init__.py
adbpy/cli.py
adbpy/constants.py
adbpy/exceptions.py
adbpy/interface.py
adbd_py-0.0.1.dist-info/METADATA
adbd_py-0.0.1.dist-info/WHEEL
adbd_py-0.0.1.dist-info/entry_points.txt
adbd_py-0.0.1.dist-info/top_level.txt
adbd_py-0.0.1.dist-info/RECORD
